box_auth/__init__.py
box_auth/box_auth.py
tests/__init__.py
tests/test_auth.py
box_oauth-0.3.1.dist-info/LICENSE.txt
box_oauth-0.3.1.dist-info/METADATA
box_oauth-0.3.1.dist-info/WHEEL
box_oauth-0.3.1.dist-info/top_level.txt
box_oauth-0.3.1.dist-info/zip-safe
box_oauth-0.3.1.dist-info/RECORD
