Metadata-Version: 2.1
Name: box-oauth
Version: 0.3.1
Summary: Box headless OAuth2 client
Home-page: UNKNOWN
Author: Gabriel Abud
Author-email: gabriel.jabud@gmail.com
License: UNKNOWN
Platform: UNKNOWN
Requires-Dist: appnope (==0.1.0)
Requires-Dist: asn1crypto (==0.24.0)
Requires-Dist: atomicwrites (==1.3.0)
Requires-Dist: attrs (==19.1.0)
Requires-Dist: autopep8 (==1.4.3)
Requires-Dist: backcall (==0.1.0)
Requires-Dist: bleach (==3.1.0)
Requires-Dist: boxsdk (==2.3.2)
Requires-Dist: certifi (==2019.3.9)
Requires-Dist: cffi (==1.12.2)
Requires-Dist: chardet (==3.0.4)
Requires-Dist: cryptography (==2.6.1)
Requires-Dist: decorator (==4.4.0)
Requires-Dist: docutils (==0.14)
Requires-Dist: entrypoints (==0.3)
Requires-Dist: idna (==2.8)
Requires-Dist: ipykernel (==5.1.0)
Requires-Dist: ipython (==7.4.0)
Requires-Dist: ipython-genutils (==0.2.0)
Requires-Dist: jedi (==0.13.3)
Requires-Dist: jupyter-client (==5.2.4)
Requires-Dist: jupyter-core (==4.4.0)
Requires-Dist: keyring (==19.0.1)
Requires-Dist: keyrings.alt (==3.1.1)
Requires-Dist: more-itertools (==7.0.0)
Requires-Dist: parso (==0.4.0)
Requires-Dist: pexpect (==4.7.0)
Requires-Dist: pickleshare (==0.7.5)
Requires-Dist: pkginfo (==1.5.0.1)
Requires-Dist: pluggy (==0.9.0)
Requires-Dist: prompt-toolkit (==2.0.9)
Requires-Dist: ptyprocess (==0.6.0)
Requires-Dist: py (==1.8.0)
Requires-Dist: pycodestyle (==2.5.0)
Requires-Dist: pycparser (==2.19)
Requires-Dist: Pygments (==2.3.1)
Requires-Dist: PyJWT (==1.7.1)
Requires-Dist: pytest (==4.4.0)
Requires-Dist: python-dateutil (==2.8.0)
Requires-Dist: pyzmq (==18.0.1)
Requires-Dist: readme-renderer (==24.0)
Requires-Dist: requests (==2.21.0)
Requires-Dist: requests-toolbelt (==0.9.1)
Requires-Dist: selenium (==3.141.0)
Requires-Dist: six (==1.12.0)
Requires-Dist: tornado (==6.0.2)
Requires-Dist: tqdm (==4.31.1)
Requires-Dist: traitlets (==4.3.2)
Requires-Dist: twine (==1.13.0)
Requires-Dist: urllib3 (==1.24.3)
Requires-Dist: wcwidth (==0.1.7)
Requires-Dist: webencodings (==0.5.1)
Requires-Dist: wrapt (==1.11.1)
